{"cameraMode":{"drawMode":0,"name":"Shaded","section":"Shading Mode"},"sceneLighting":true,"audioPlay":false,"sceneViewState":{"showFog":true,"showMaterialUpdate":false,"showSkybox":true,"showFlares":true,"showImageEffects":true,"showParticleSystems":true,"showVisualEffectGraphs":true,"m_FxEnabled":true},"in2DMode":false,"pivot":{"x":-45.42334747314453,"y":3.824321746826172,"z":46.575347900390628},"rotation":{"x":-0.2927536368370056,"y":-0.39458906650543215,"z":0.1342279464006424,"w":-0.8605855107307434},"size":63.67002487182617,"orthographic":false}